LICENSE.txt
MANIFEST.in
README.md
requirements-tests.txt
setup.cfg
setup.py
py_look_for_timeouts/__init__.py
py_look_for_timeouts/main.py
py_look_for_timeouts.egg-info/PKG-INFO
py_look_for_timeouts.egg-info/SOURCES.txt
py_look_for_timeouts.egg-info/dependency_links.txt
py_look_for_timeouts.egg-info/entry_points.txt
py_look_for_timeouts.egg-info/top_level.txt