Metadata-Version: 1.1
Name: py-look-for-timeouts
Version: 0.3
Summary: ple python ast consumer which searches for missing timeouts
Home-page: https://github.com/uber/py-look-for-timeouts
Author: James Brown
Author-email: jbrown@uber.com
License: MIT (Expat)
Platform: UNKNOWN
Classifier: Programming Language :: Python
Classifier: Operating System :: OS Independent
Classifier: Topic :: Security
Classifier: Topic :: Security
Classifier: Intended Audience :: Developers
Classifier: Development Status :: 3 - Alpha
Classifier: Programming Language :: Python :: 2.7
Classifier: License :: OSI Approved :: MIT License
